penguin_logistics/__init__.py
penguin_logistics/__main__.py
penguin_logistics/batch/__init__.py
penguin_logistics/core/__init__.py
penguin_logistics/fake_cache/__init__.py
penguin_logistics/parallel/__init__.py
penguin_logistics-0.0.2.dist-info/METADATA
penguin_logistics-0.0.2.dist-info/WHEEL
penguin_logistics-0.0.2.dist-info/top_level.txt
penguin_logistics-0.0.2.dist-info/RECORD
